.DS_Store
.coveragerc
.gitignore
AUTHORS.rst
CHANGELOG.rst
LICENSE.txt
README.rst
requirements.txt
setup.cfg
setup.py
docs/.DS_Store
docs/Makefile
docs/authors.rst
docs/changelog.rst
docs/conf.py
docs/index.rst
docs/license.rst
docs/_static/.gitignore
src/.DS_Store
src/transplanttoolbox_victor/.DS_Store
src/transplanttoolbox_victor/UNOS_4-10_ag_equivalencies.csv
src/transplanttoolbox_victor/UNOS_UA_ag_equivalencies.csv
src/transplanttoolbox_victor/UNOS_antigens_to_alleles.csv
src/transplanttoolbox_victor/UNOS_conversion_table.csv
src/transplanttoolbox_victor/UNOS_conversion_table_with_rules.csv
src/transplanttoolbox_victor/__init__.py
src/transplanttoolbox_victor/conversion_functions.py
src/transplanttoolbox_victor/conversion_functions_for_VXM.py
src/transplanttoolbox_victor/conversion_table.csv
src/transplanttoolbox_victor/reverse_conversion.py
src/transplanttoolbox_victor/reverse_conversion_27.py
src/transplanttoolbox_victor/reverse_table.py
src/transplanttoolbox_victor/skeleton.py
src/transplanttoolbox_victor/virtual_crossmatch.py
src/transplanttoolbox_victor/vxm_hla.py
src/transplanttoolbox_victor.egg-info/PKG-INFO
src/transplanttoolbox_victor.egg-info/SOURCES.txt
src/transplanttoolbox_victor.egg-info/dependency_links.txt
src/transplanttoolbox_victor.egg-info/entry_points.txt
src/transplanttoolbox_victor.egg-info/not-zip-safe
src/transplanttoolbox_victor.egg-info/requires.txt
src/transplanttoolbox_victor.egg-info/top_level.txt
src/transplanttoolbox_victor/freqs_6loc/AAFA.ARS.freqs
src/transplanttoolbox_victor/freqs_6loc/AFA.ARS.freqs
src/transplanttoolbox_victor/freqs_6loc/AFB.ARS.freqs
src/transplanttoolbox_victor/freqs_6loc/AINDI.ARS.freqs
src/transplanttoolbox_victor/freqs_6loc/AISC.ARS.freqs
src/transplanttoolbox_victor/freqs_6loc/ALANAM.ARS.freqs
src/transplanttoolbox_victor/freqs_6loc/AMIND.ARS.freqs
src/transplanttoolbox_victor/freqs_6loc/API.ARS.freqs
src/transplanttoolbox_victor/freqs_6loc/CARB.ARS.freqs
src/transplanttoolbox_victor/freqs_6loc/CARHIS.ARS.freqs
src/transplanttoolbox_victor/freqs_6loc/CARIBI.ARS.freqs
src/transplanttoolbox_victor/freqs_6loc/CAU.ARS.freqs
src/transplanttoolbox_victor/freqs_6loc/EURCAU.ARS.freqs
src/transplanttoolbox_victor/freqs_6loc/FILII.ARS.freqs
src/transplanttoolbox_victor/freqs_6loc/HAWI.ARS.freqs
src/transplanttoolbox_victor/freqs_6loc/HIS.ARS.freqs
