Metadata-Version: 1.1
Name: transplanttoolbox-victor
Version: 1.0.0.1
Summary: Virtual Crossmatch for molecular HLA typing data
Home-page: http://transplanttoolbox.org/victor
Author: Gragert Lab
Author-email: pathologygragertlab@tulane.edu
License: GNU GPL3
Platform: any
Classifier: Development Status :: 4 - Beta
Classifier: Programming Language :: Python
